wetransfer/__init__.py
wetransfer/api_requests.py
wetransfer/client.py
wetransfer/items.py
wetransfer/logger.py
wetransfer/transfer.py
wetransfer/version.py
wetransfer-0.2.0.dist-info/LICENSE.txt
wetransfer-0.2.0.dist-info/METADATA
wetransfer-0.2.0.dist-info/RECORD
wetransfer-0.2.0.dist-info/WHEEL
wetransfer-0.2.0.dist-info/top_level.txt
wetransfer-0.2.0.dist-info/zip-safe
