Metadata-Version: 2.1
Name: wetransfer
Version: 0.2.0
Summary: A Python SDK for WeTransfer's Public API
Home-page: https://github.com/astrikos/wetransfer-python-sdk
Author: Andreas Strikos
Author-email: andreas@wetransfer.com
Maintainer: Andreas Strikos
Maintainer-email: andreas@wetransfer.com
License: UNKNOWN
Download-URL: https://github.com/astrikos/wetransfer-python-sdk
Platform: UNKNOWN
Classifier: Development Status :: 3 - Alpha
Classifier: Intended Audience :: Developers
Classifier: Natural Language :: English
Classifier: Operating System :: OS Independent
Classifier: License :: OSI Approved :: GNU General Public License v3 (GPLv3)
Classifier: Programming Language :: Python
Classifier: Programming Language :: Python :: 2
Classifier: Programming Language :: Python :: 2.7
Classifier: Programming Language :: Python :: 3
Classifier: Programming Language :: Python :: 3.5
Classifier: Programming Language :: Python :: 3.6
Classifier: Programming Language :: Python :: 3.7
Classifier: Programming Language :: Python :: Implementation :: CPython
Classifier: Programming Language :: Python :: Implementation :: PyPy
Classifier: Topic :: Software Development :: Libraries :: Python Modules
Classifier: Topic :: Internet :: WWW/HTTP
Requires-Dist: requests (>=2.7.0)
Requires-Dist: six
